{
  "produtos": [
    {
      "id": 1,
      "nome": "arroz",
      "quantidade": 10,
      "preco": 5,
      "peso": 1,
      "foto": "https://www.designi.com.br/images/preview/10001834.jpg"
    },
    {
      "id": 2,
      "nome": "arroz",
      "quantidade": 10,
      "preco": 5,
      "peso": 1,
      "foto": "https://www.designi.com.br/images/preview/10001834.jpg"
    },
    {
      "id": 3,
      "nome": "leite",
      "quantidade": "10",
      "preco": "5",
      "peso": "1",
      "foto": ""
    }
  ]
}